LICENSE.md
monitor_common/__init__.py
monitor_common/mongodb/__init__.py
monitor_common/mongodb/status_entry.py
monitor_common/queries.py
monitor_common/status.py
monitor_common-0.2.0.dist-info/LICENSE.md
monitor_common-0.2.0.dist-info/WHEEL
monitor_common-0.2.0.dist-info/METADATA
monitor_common-0.2.0.dist-info/RECORD
